Metadata-Version: 2.1
Name: spacie
Version: 0.0.3
Summary: Space sync app
Home-page: https://github.com/Tsangares/Spacy
Author: William Wyatt
Author-email: tsangares@gmail.com
License: UNKNOWN
Platform: UNKNOWN
Classifier: Programming Language :: Python :: 3
Classifier: License :: OSI Approved :: MIT License
